Metadata-Version: 2.1
Name: jyjdbc
Version: 0.0.5
Summary: Pure Jython (Python in the JVM) JDBC dbapi pep-249 driver
Home-page: https://hg.sr.ht/~clach04/jyjdbc
Author: Chris Clark
Maintainer: Chris Clark
License: LGPLv2.1
Platform: any
Classifier: Environment :: Other Environment
Classifier: License :: OSI Approved :: GNU Library or Lesser General Public License (LGPL)
Classifier: Intended Audience :: Developers
Classifier: Operating System :: OS Independent
Classifier: Operating System :: Microsoft :: Windows :: Windows NT/2000
Classifier: Operating System :: POSIX
Classifier: Operating System :: POSIX :: Linux
Classifier: Operating System :: Unix
Classifier: Programming Language :: Python
Classifier: Programming Language :: Python :: 2
Classifier: Programming Language :: Python :: 2.7
Classifier: Programming Language :: Python :: 2.5
Classifier: Programming Language :: Python :: Implementation :: Jython
Classifier: Programming Language :: SQL
Classifier: Topic :: Database
License-File: LICENSE
